hannakageul/__init__.py
hannakageul/decoder.py
hannakageul/encoder.py
hannakageul/convert/__init__.py
hannakageul/convert/euccn.py
hannakageul/convert/eucjp.py
hannakageul/convert/euckr.py
hannakageul/convert/jis.py
hannakageul/convert/sjis.py
hannakageul/convert/utf8.py
hannakageul-0.1.2.dist-info/DESCRIPTION.rst
hannakageul-0.1.2.dist-info/METADATA
hannakageul-0.1.2.dist-info/RECORD
hannakageul-0.1.2.dist-info/WHEEL
hannakageul-0.1.2.dist-info/metadata.json
hannakageul-0.1.2.dist-info/top_level.txt
