Metadata-Version: 2.0
Name: hannakageul
Version: 0.1.2
Summary: Hangeul - Kana encoding converter
Home-page: https://github.com/noxowl/hannakageul
Author: Mirai Kim
Author-email: nachtbeere@outlook.com
License: MIT
Keywords: charset,encoding,converter,euc-kr,shift-jis
Platform: UNKNOWN
Classifier: Development Status :: 3 - Alpha
Classifier: Intended Audience :: Developers
Classifier: License :: OSI Approved :: MIT License
Classifier: Natural Language :: Korean
Classifier: Natural Language :: Japanese
Classifier: Programming Language :: Python :: 3.5
